local_operator/__init__.py
local_operator/admin.py
local_operator/agents.py
local_operator/bootstrap.py
local_operator/cli.py
local_operator/config.py
local_operator/console.py
local_operator/credentials.py
local_operator/env.py
local_operator/executor.py
local_operator/helpers.py
local_operator/jobs.py
local_operator/logger.py
local_operator/mocks.py
local_operator/notebook.py
local_operator/operator.py
local_operator/prompts.py
local_operator/scheduler_service.py
local_operator/stream.py
local_operator/types.py
local_operator/clients/__init__.py
local_operator/clients/fal.py
local_operator/clients/google_client.py
local_operator/clients/ollama.py
local_operator/clients/openrouter.py
local_operator/clients/radient.py
local_operator/clients/serpapi.py
local_operator/clients/tavily.py
local_operator/model/__init__.py
local_operator/model/configure.py
local_operator/model/registry.py
local_operator/server/__init__.py
local_operator/server/app.py
local_operator/server/dependencies.py
local_operator/server/generate_openapi.py
local_operator/server/openapi.py
local_operator/server/models/__init__.py
local_operator/server/models/schemas.py
local_operator/server/routes/__init__.py
local_operator/server/routes/agents.py
local_operator/server/routes/chat.py
local_operator/server/routes/config.py
local_operator/server/routes/credentials.py
local_operator/server/routes/health.py
local_operator/server/routes/jobs.py
local_operator/server/routes/models.py
local_operator/server/routes/schedules.py
local_operator/server/routes/speech.py
local_operator/server/routes/static.py
local_operator/server/routes/transcription.py
local_operator/server/routes/websockets.py
local_operator/server/utils/__init__.py
local_operator/server/utils/attachment_utils.py
local_operator/server/utils/job_processor.py
local_operator/server/utils/job_processor_queue.py
local_operator/server/utils/operator.py
local_operator/server/utils/speech_utils.py
local_operator/server/utils/websocket_manager.py
local_operator-0.15.9.dist-info/licenses/LICENSE
local_operator-0.15.9.dist-info/METADATA
local_operator-0.15.9.dist-info/WHEEL
local_operator-0.15.9.dist-info/entry_points.txt
local_operator-0.15.9.dist-info/top_level.txt
local_operator-0.15.9.dist-info/RECORD
