Metadata-Version: 2.4
Name: local-operator
Version: 0.15.9
Summary: A team of proactive AI assistants that can work together behind the scenes to help you get mundane tasks done so you can focus on the fun stuff.
Author-email: Damian Tran <damian@radienthq.com>
License: # GNU GENERAL PUBLIC LICENSE
Project-URL: Homepage, https://github.com/damianvtran/local-operator
Keywords: local,agent,execution,operator,agent-to-agent,agentic,local-first,ai,proactive
Classifier: License :: OSI Approved :: GNU General Public License v3 (GPLv3)
Classifier: Programming Language :: Python
Classifier: Programming Language :: Python :: 3.12
Requires-Python: >=3.12
License-File: LICENSE
Requires-Dist: langchain-openai
Requires-Dist: langchain-ollama
Requires-Dist: langchain-anthropic
Requires-Dist: langchain-google-genai
Requires-Dist: langchain
Requires-Dist: langchain-community
Requires-Dist: python-dotenv
Requires-Dist: pydantic
Requires-Dist: tiktoken
Requires-Dist: uvicorn
Requires-Dist: fastapi
Requires-Dist: playwright
Requires-Dist: requests
Requires-Dist: psutil
Requires-Dist: dill
Requires-Dist: pyreadline3
Requires-Dist: jsonlines
Requires-Dist: python-multipart
Requires-Dist: apscheduler
Requires-Dist: pillow
Requires-Dist: pillow-heif
Requires-Dist: browser-use==0.1.45
Requires-Dist: python-dateutil>=2.8.0
Requires-Dist: six>=1.16.0
Requires-Dist: faiss-cpu==1.10.0
Requires-Dist: certifi>=2024.7.4
Requires-Dist: configobj>=5.0.9
Requires-Dist: cryptography>=43.0.1
Requires-Dist: idna>=3.7
Requires-Dist: jinja2>=3.1.5
Requires-Dist: requests>=2.32.0
Requires-Dist: twisted>=24.7.0rc1
Requires-Dist: urllib3>=2.2.2
Requires-Dist: websockets>=15.0.1
Requires-Dist: setuptools>=78.1.1
Provides-Extra: dev
Requires-Dist: black; extra == "dev"
Requires-Dist: isort; extra == "dev"
Requires-Dist: pylint; extra == "dev"
Requires-Dist: pyright; extra == "dev"
Requires-Dist: pytest; extra == "dev"
Requires-Dist: pytest-asyncio; extra == "dev"
Requires-Dist: pip-audit; extra == "dev"
Dynamic: license-file
Dynamic: requires-python
